ezjt/__init__.py
ezjt/test_basic.py
ez_json_traverse-0.3.3.dist-info/LICENSE
ez_json_traverse-0.3.3.dist-info/METADATA
ez_json_traverse-0.3.3.dist-info/WHEEL
ez_json_traverse-0.3.3.dist-info/top_level.txt
ez_json_traverse-0.3.3.dist-info/RECORD
