Metadata-Version: 2.1
Name: ez-json-traverse
Version: 0.3.3
Summary: Easier traversing and exploration of JSON structures
Home-page: https://github.com/buhanec/ez-json-traverse
Author: buhanec
License: MIT
Platform: UNKNOWN
Classifier: Programming Language :: Python :: 3
Classifier: Programming Language :: Python :: 3.6
Classifier: Programming Language :: Python :: 3.7
Classifier: License :: OSI Approved :: MIT License
Classifier: Operating System :: OS Independent
